{"cameraMode":{"drawMode":0,"name":"Shaded","section":"Shading Mode"},"sceneLighting":true,"audioPlay":false,"sceneViewState":{"m_AlwaysRefresh":false,"showFog":true,"showSkybox":true,"showFlares":true,"showImageEffects":true,"showParticleSystems":true,"showVisualEffectGraphs":true,"m_FxEnabled":true},"in2DMode":false,"pivot":{"x":9.526958465576172,"y":2.7580227851867677,"z":0.2240050733089447},"rotation":{"x":-0.11704522371292114,"y":0.7538118362426758,"z":-0.13974694907665254,"w":-0.6313251256942749},"size":1.2869962453842164,"orthographic":false}